LICENSE.txt
MANIFEST.in
README.rst
setup.cfg
setup.py
alohomora/__init__.py
alohomora/alohomora.dat
alohomora/authenticate.py
config/__init__.py
data/data_file
fynd_django_alohomora.egg-info/PKG-INFO
fynd_django_alohomora.egg-info/SOURCES.txt
fynd_django_alohomora.egg-info/dependency_links.txt
fynd_django_alohomora.egg-info/entry_points.txt
fynd_django_alohomora.egg-info/requires.txt
fynd_django_alohomora.egg-info/top_level.txt
helpers/__init__.py
helpers/misc_hepler.py
libs/__init__.py
libs/auth.py